{
    "setting": {
        "title": "flex对齐",
        "order": 5
    },
    "catalogs": [],
    "contents": "<p>给<code>Row</code>添加<code>align</code>属性，即可自动启用<code>flex</code>布局来定义<code>Col</code>垂直方向的排列方式，它的可选值为：<code>top</code> <code>bottom</code> <code>middle</code> <code>stretch</code> <code>baseline</code></p>\n",
    "index": 193,
    "highlighted": [
        {
            "language": "vdt",
            "content": "<pre><code class=\"hljs jsx\"><span class=\"hljs-keyword\">import</span> {Row, Col} <span class=\"hljs-keyword\">from</span> <span class=\"hljs-string\">'kpc/components/grid'</span>;\n\n<span class=\"xml\"><span class=\"hljs-tag\">&lt;<span class=\"hljs-name\">div</span>&gt;</span>\n    <span class=\"hljs-tag\">&lt;<span class=\"hljs-name\">h5</span>&gt;</span>顶端对齐 top<span class=\"hljs-tag\">&lt;/<span class=\"hljs-name\">h5</span>&gt;</span>\n    <span class=\"hljs-tag\">&lt;<span class=\"hljs-name\">Row</span> <span class=\"hljs-attr\">align</span>=<span class=\"hljs-string\">\"top\"</span> <span class=\"hljs-attr\">justify</span>=<span class=\"hljs-string\">\"center\"</span>&gt;</span> \n        <span class=\"hljs-tag\">&lt;<span class=\"hljs-name\">Col</span> <span class=\"hljs-attr\">span</span>=<span class=\"hljs-string\">\"4\"</span> <span class=\"hljs-attr\">style</span>=<span class=\"hljs-string\">\"height: 100px\"</span>&gt;</span>col-4<span class=\"hljs-tag\">&lt;/<span class=\"hljs-name\">Col</span>&gt;</span>\n        <span class=\"hljs-tag\">&lt;<span class=\"hljs-name\">Col</span> <span class=\"hljs-attr\">span</span>=<span class=\"hljs-string\">\"4\"</span> <span class=\"hljs-attr\">style</span>=<span class=\"hljs-string\">\"height: 60px\"</span>&gt;</span>col-4<span class=\"hljs-tag\">&lt;/<span class=\"hljs-name\">Col</span>&gt;</span>\n        <span class=\"hljs-tag\">&lt;<span class=\"hljs-name\">Col</span> <span class=\"hljs-attr\">span</span>=<span class=\"hljs-string\">\"4\"</span> <span class=\"hljs-attr\">style</span>=<span class=\"hljs-string\">\"height: 80px\"</span>&gt;</span>col-4<span class=\"hljs-tag\">&lt;/<span class=\"hljs-name\">Col</span>&gt;</span>\n        <span class=\"hljs-tag\">&lt;<span class=\"hljs-name\">Col</span> <span class=\"hljs-attr\">span</span>=<span class=\"hljs-string\">\"4\"</span> <span class=\"hljs-attr\">style</span>=<span class=\"hljs-string\">\"height: 40px\"</span>&gt;</span>col-4<span class=\"hljs-tag\">&lt;/<span class=\"hljs-name\">Col</span>&gt;</span>\n    <span class=\"hljs-tag\">&lt;/<span class=\"hljs-name\">Row</span>&gt;</span>\n    <span class=\"hljs-tag\">&lt;<span class=\"hljs-name\">h5</span>&gt;</span>底部对齐 bottom<span class=\"hljs-tag\">&lt;/<span class=\"hljs-name\">h5</span>&gt;</span>\n    <span class=\"hljs-tag\">&lt;<span class=\"hljs-name\">Row</span> <span class=\"hljs-attr\">align</span>=<span class=\"hljs-string\">\"bottom\"</span> <span class=\"hljs-attr\">justify</span>=<span class=\"hljs-string\">\"center\"</span>&gt;</span> \n        <span class=\"hljs-tag\">&lt;<span class=\"hljs-name\">Col</span> <span class=\"hljs-attr\">span</span>=<span class=\"hljs-string\">\"4\"</span> <span class=\"hljs-attr\">style</span>=<span class=\"hljs-string\">\"height: 100px\"</span>&gt;</span>col-4<span class=\"hljs-tag\">&lt;/<span class=\"hljs-name\">Col</span>&gt;</span>\n        <span class=\"hljs-tag\">&lt;<span class=\"hljs-name\">Col</span> <span class=\"hljs-attr\">span</span>=<span class=\"hljs-string\">\"4\"</span> <span class=\"hljs-attr\">style</span>=<span class=\"hljs-string\">\"height: 60px\"</span>&gt;</span>col-4<span class=\"hljs-tag\">&lt;/<span class=\"hljs-name\">Col</span>&gt;</span>\n        <span class=\"hljs-tag\">&lt;<span class=\"hljs-name\">Col</span> <span class=\"hljs-attr\">span</span>=<span class=\"hljs-string\">\"4\"</span> <span class=\"hljs-attr\">style</span>=<span class=\"hljs-string\">\"height: 80px\"</span>&gt;</span>col-4<span class=\"hljs-tag\">&lt;/<span class=\"hljs-name\">Col</span>&gt;</span>\n        <span class=\"hljs-tag\">&lt;<span class=\"hljs-name\">Col</span> <span class=\"hljs-attr\">span</span>=<span class=\"hljs-string\">\"4\"</span> <span class=\"hljs-attr\">style</span>=<span class=\"hljs-string\">\"height: 40px\"</span>&gt;</span>col-4<span class=\"hljs-tag\">&lt;/<span class=\"hljs-name\">Col</span>&gt;</span>\n    <span class=\"hljs-tag\">&lt;/<span class=\"hljs-name\">Row</span>&gt;</span>\n    <span class=\"hljs-tag\">&lt;<span class=\"hljs-name\">h5</span>&gt;</span>居中对齐 middle<span class=\"hljs-tag\">&lt;/<span class=\"hljs-name\">h5</span>&gt;</span>\n    <span class=\"hljs-tag\">&lt;<span class=\"hljs-name\">Row</span> <span class=\"hljs-attr\">align</span>=<span class=\"hljs-string\">\"middle\"</span> <span class=\"hljs-attr\">justify</span>=<span class=\"hljs-string\">\"center\"</span>&gt;</span> \n        <span class=\"hljs-tag\">&lt;<span class=\"hljs-name\">Col</span> <span class=\"hljs-attr\">span</span>=<span class=\"hljs-string\">\"4\"</span> <span class=\"hljs-attr\">style</span>=<span class=\"hljs-string\">\"height: 100px\"</span>&gt;</span>col-4<span class=\"hljs-tag\">&lt;/<span class=\"hljs-name\">Col</span>&gt;</span>\n        <span class=\"hljs-tag\">&lt;<span class=\"hljs-name\">Col</span> <span class=\"hljs-attr\">span</span>=<span class=\"hljs-string\">\"4\"</span> <span class=\"hljs-attr\">style</span>=<span class=\"hljs-string\">\"height: 60px\"</span>&gt;</span>col-4<span class=\"hljs-tag\">&lt;/<span class=\"hljs-name\">Col</span>&gt;</span>\n        <span class=\"hljs-tag\">&lt;<span class=\"hljs-name\">Col</span> <span class=\"hljs-attr\">span</span>=<span class=\"hljs-string\">\"4\"</span> <span class=\"hljs-attr\">style</span>=<span class=\"hljs-string\">\"height: 80px\"</span>&gt;</span>col-4<span class=\"hljs-tag\">&lt;/<span class=\"hljs-name\">Col</span>&gt;</span>\n        <span class=\"hljs-tag\">&lt;<span class=\"hljs-name\">Col</span> <span class=\"hljs-attr\">span</span>=<span class=\"hljs-string\">\"4\"</span> <span class=\"hljs-attr\">style</span>=<span class=\"hljs-string\">\"height: 40px\"</span>&gt;</span>col-4<span class=\"hljs-tag\">&lt;/<span class=\"hljs-name\">Col</span>&gt;</span>\n    <span class=\"hljs-tag\">&lt;/<span class=\"hljs-name\">Row</span>&gt;</span>\n    <span class=\"hljs-tag\">&lt;<span class=\"hljs-name\">h5</span>&gt;</span>撑开成容器高度 stretch<span class=\"hljs-tag\">&lt;/<span class=\"hljs-name\">h5</span>&gt;</span>\n    <span class=\"hljs-tag\">&lt;<span class=\"hljs-name\">Row</span> <span class=\"hljs-attr\">align</span>=<span class=\"hljs-string\">\"stretch\"</span> <span class=\"hljs-attr\">justify</span>=<span class=\"hljs-string\">\"center\"</span> <span class=\"hljs-attr\">style</span>=<span class=\"hljs-string\">\"height: 100px;\"</span>&gt;</span> \n        <span class=\"hljs-tag\">&lt;<span class=\"hljs-name\">Col</span> <span class=\"hljs-attr\">span</span>=<span class=\"hljs-string\">\"4\"</span>&gt;</span>col-4<span class=\"hljs-tag\">&lt;/<span class=\"hljs-name\">Col</span>&gt;</span>\n        <span class=\"hljs-tag\">&lt;<span class=\"hljs-name\">Col</span> <span class=\"hljs-attr\">span</span>=<span class=\"hljs-string\">\"4\"</span>&gt;</span>col-4<span class=\"hljs-tag\">&lt;/<span class=\"hljs-name\">Col</span>&gt;</span>\n        <span class=\"hljs-tag\">&lt;<span class=\"hljs-name\">Col</span> <span class=\"hljs-attr\">span</span>=<span class=\"hljs-string\">\"4\"</span>&gt;</span>col-4<span class=\"hljs-tag\">&lt;/<span class=\"hljs-name\">Col</span>&gt;</span>\n        <span class=\"hljs-tag\">&lt;<span class=\"hljs-name\">Col</span> <span class=\"hljs-attr\">span</span>=<span class=\"hljs-string\">\"4\"</span>&gt;</span>col-4<span class=\"hljs-tag\">&lt;/<span class=\"hljs-name\">Col</span>&gt;</span>\n    <span class=\"hljs-tag\">&lt;/<span class=\"hljs-name\">Row</span>&gt;</span>\n    <span class=\"hljs-tag\">&lt;<span class=\"hljs-name\">h5</span>&gt;</span>基线对齐 baseline<span class=\"hljs-tag\">&lt;/<span class=\"hljs-name\">h5</span>&gt;</span>\n    <span class=\"hljs-tag\">&lt;<span class=\"hljs-name\">Row</span> <span class=\"hljs-attr\">align</span>=<span class=\"hljs-string\">\"baseline\"</span> <span class=\"hljs-attr\">justify</span>=<span class=\"hljs-string\">\"center\"</span>&gt;</span> \n        <span class=\"hljs-tag\">&lt;<span class=\"hljs-name\">Col</span> <span class=\"hljs-attr\">span</span>=<span class=\"hljs-string\">\"4\"</span> <span class=\"hljs-attr\">style</span>=<span class=\"hljs-string\">\"height: 100px; font-size: 20px\"</span>&gt;</span>col-4<span class=\"hljs-tag\">&lt;/<span class=\"hljs-name\">Col</span>&gt;</span>\n        <span class=\"hljs-tag\">&lt;<span class=\"hljs-name\">Col</span> <span class=\"hljs-attr\">span</span>=<span class=\"hljs-string\">\"4\"</span> <span class=\"hljs-attr\">style</span>=<span class=\"hljs-string\">\"height: 60px; font-size: 16px\"</span>&gt;</span>col-4<span class=\"hljs-tag\">&lt;/<span class=\"hljs-name\">Col</span>&gt;</span>\n        <span class=\"hljs-tag\">&lt;<span class=\"hljs-name\">Col</span> <span class=\"hljs-attr\">span</span>=<span class=\"hljs-string\">\"4\"</span> <span class=\"hljs-attr\">style</span>=<span class=\"hljs-string\">\"height: 80px; font-size: 28px\"</span>&gt;</span>col-4<span class=\"hljs-tag\">&lt;/<span class=\"hljs-name\">Col</span>&gt;</span>\n        <span class=\"hljs-tag\">&lt;<span class=\"hljs-name\">Col</span> <span class=\"hljs-attr\">span</span>=<span class=\"hljs-string\">\"4\"</span> <span class=\"hljs-attr\">style</span>=<span class=\"hljs-string\">\"height: 40px; font-size: 12px\"</span>&gt;</span>col-4<span class=\"hljs-tag\">&lt;/<span class=\"hljs-name\">Col</span>&gt;</span>\n    <span class=\"hljs-tag\">&lt;/<span class=\"hljs-name\">Row</span>&gt;</span>\n<span class=\"hljs-tag\">&lt;/<span class=\"hljs-name\">div</span>&gt;</span></span></code></pre>"
        },
        {
            "language": "styl",
            "content": "<pre><code class=\"hljs styl\"><span class=\"hljs-selector-class\">.k-col</span>\n    <span class=\"hljs-attribute\">line-height</span> <span class=\"hljs-number\">40px</span>\n    <span class=\"hljs-attribute\">text-align</span> center\n    <span class=\"hljs-attribute\">color</span> <span class=\"hljs-number\">#fff</span>\n    &amp;:nth-of-type(even)\n        <span class=\"hljs-attribute\">background</span> <span class=\"hljs-number\">#0a5eee</span>\n    &amp;:nth-of-type(odd)\n        <span class=\"hljs-attribute\">background</span> lighten(<span class=\"hljs-number\">#0a5eee</span>, <span class=\"hljs-number\">30%</span>)\n<span class=\"hljs-selector-class\">.k-row</span>\n    <span class=\"hljs-attribute\">margin-bottom</span> <span class=\"hljs-number\">20px</span>\n    <span class=\"hljs-attribute\">padding</span> <span class=\"hljs-number\">10px</span> <span class=\"hljs-number\">0</span>\n    <span class=\"hljs-attribute\">background</span> <span class=\"hljs-number\">#e5e5e5</span>\n<span class=\"hljs-selector-tag\">h5</span>\n    <span class=\"hljs-attribute\">margin-bottom</span> <span class=\"hljs-number\">8px</span></code></pre>"
        },
        {
            "language": "js",
            "content": "<pre><code class=\"hljs js\"><span class=\"hljs-keyword\">import</span> Intact <span class=\"hljs-keyword\">from</span> <span class=\"hljs-string\">'intact'</span>;\n<span class=\"hljs-keyword\">import</span> template <span class=\"hljs-keyword\">from</span> <span class=\"hljs-string\">'./index.vdt'</span>;\n<span class=\"hljs-keyword\">import</span> <span class=\"hljs-string\">'./index.styl'</span>; \n\n<span class=\"hljs-keyword\">export</span> <span class=\"hljs-keyword\">default</span> <span class=\"hljs-class\"><span class=\"hljs-keyword\">class</span> <span class=\"hljs-keyword\">extends</span> <span class=\"hljs-title\">Intact</span> </span>{\n    @Intact.template()\n    <span class=\"hljs-keyword\">static</span> template = template;\n}</code></pre>"
        },
        {
            "language": "vue",
            "content": "<pre><code class=\"hljs html\"><span class=\"hljs-tag\">&lt;<span class=\"hljs-name\">template</span>&gt;</span>\n    <span class=\"hljs-tag\">&lt;<span class=\"hljs-name\">div</span>&gt;</span>\n        <span class=\"hljs-tag\">&lt;<span class=\"hljs-name\">h5</span>&gt;</span>顶端对齐 top<span class=\"hljs-tag\">&lt;/<span class=\"hljs-name\">h5</span>&gt;</span>\n        <span class=\"hljs-tag\">&lt;<span class=\"hljs-name\">Row</span> <span class=\"hljs-attr\">align</span>=<span class=\"hljs-string\">\"top\"</span> <span class=\"hljs-attr\">justify</span>=<span class=\"hljs-string\">\"center\"</span>&gt;</span> \n            <span class=\"hljs-tag\">&lt;<span class=\"hljs-name\">Col</span> <span class=\"hljs-attr\">span</span>=<span class=\"hljs-string\">\"4\"</span> <span class=\"hljs-attr\">style</span>=<span class=\"hljs-string\">\"height: 100px\"</span>&gt;</span>col-4<span class=\"hljs-tag\">&lt;/<span class=\"hljs-name\">Col</span>&gt;</span>\n            <span class=\"hljs-tag\">&lt;<span class=\"hljs-name\">Col</span> <span class=\"hljs-attr\">span</span>=<span class=\"hljs-string\">\"4\"</span> <span class=\"hljs-attr\">style</span>=<span class=\"hljs-string\">\"height: 60px\"</span>&gt;</span>col-4<span class=\"hljs-tag\">&lt;/<span class=\"hljs-name\">Col</span>&gt;</span>\n            <span class=\"hljs-tag\">&lt;<span class=\"hljs-name\">Col</span> <span class=\"hljs-attr\">span</span>=<span class=\"hljs-string\">\"4\"</span> <span class=\"hljs-attr\">style</span>=<span class=\"hljs-string\">\"height: 80px\"</span>&gt;</span>col-4<span class=\"hljs-tag\">&lt;/<span class=\"hljs-name\">Col</span>&gt;</span>\n            <span class=\"hljs-tag\">&lt;<span class=\"hljs-name\">Col</span> <span class=\"hljs-attr\">span</span>=<span class=\"hljs-string\">\"4\"</span> <span class=\"hljs-attr\">style</span>=<span class=\"hljs-string\">\"height: 40px\"</span>&gt;</span>col-4<span class=\"hljs-tag\">&lt;/<span class=\"hljs-name\">Col</span>&gt;</span>\n        <span class=\"hljs-tag\">&lt;/<span class=\"hljs-name\">Row</span>&gt;</span>\n        <span class=\"hljs-tag\">&lt;<span class=\"hljs-name\">h5</span>&gt;</span>底部对齐 bottom<span class=\"hljs-tag\">&lt;/<span class=\"hljs-name\">h5</span>&gt;</span>\n        <span class=\"hljs-tag\">&lt;<span class=\"hljs-name\">Row</span> <span class=\"hljs-attr\">align</span>=<span class=\"hljs-string\">\"bottom\"</span> <span class=\"hljs-attr\">justify</span>=<span class=\"hljs-string\">\"center\"</span>&gt;</span> \n            <span class=\"hljs-tag\">&lt;<span class=\"hljs-name\">Col</span> <span class=\"hljs-attr\">span</span>=<span class=\"hljs-string\">\"4\"</span> <span class=\"hljs-attr\">style</span>=<span class=\"hljs-string\">\"height: 100px\"</span>&gt;</span>col-4<span class=\"hljs-tag\">&lt;/<span class=\"hljs-name\">Col</span>&gt;</span>\n            <span class=\"hljs-tag\">&lt;<span class=\"hljs-name\">Col</span> <span class=\"hljs-attr\">span</span>=<span class=\"hljs-string\">\"4\"</span> <span class=\"hljs-attr\">style</span>=<span class=\"hljs-string\">\"height: 60px\"</span>&gt;</span>col-4<span class=\"hljs-tag\">&lt;/<span class=\"hljs-name\">Col</span>&gt;</span>\n            <span class=\"hljs-tag\">&lt;<span class=\"hljs-name\">Col</span> <span class=\"hljs-attr\">span</span>=<span class=\"hljs-string\">\"4\"</span> <span class=\"hljs-attr\">style</span>=<span class=\"hljs-string\">\"height: 80px\"</span>&gt;</span>col-4<span class=\"hljs-tag\">&lt;/<span class=\"hljs-name\">Col</span>&gt;</span>\n            <span class=\"hljs-tag\">&lt;<span class=\"hljs-name\">Col</span> <span class=\"hljs-attr\">span</span>=<span class=\"hljs-string\">\"4\"</span> <span class=\"hljs-attr\">style</span>=<span class=\"hljs-string\">\"height: 40px\"</span>&gt;</span>col-4<span class=\"hljs-tag\">&lt;/<span class=\"hljs-name\">Col</span>&gt;</span>\n        <span class=\"hljs-tag\">&lt;/<span class=\"hljs-name\">Row</span>&gt;</span>\n        <span class=\"hljs-tag\">&lt;<span class=\"hljs-name\">h5</span>&gt;</span>居中对齐 middle<span class=\"hljs-tag\">&lt;/<span class=\"hljs-name\">h5</span>&gt;</span>\n        <span class=\"hljs-tag\">&lt;<span class=\"hljs-name\">Row</span> <span class=\"hljs-attr\">align</span>=<span class=\"hljs-string\">\"middle\"</span> <span class=\"hljs-attr\">justify</span>=<span class=\"hljs-string\">\"center\"</span>&gt;</span> \n            <span class=\"hljs-tag\">&lt;<span class=\"hljs-name\">Col</span> <span class=\"hljs-attr\">span</span>=<span class=\"hljs-string\">\"4\"</span> <span class=\"hljs-attr\">style</span>=<span class=\"hljs-string\">\"height: 100px\"</span>&gt;</span>col-4<span class=\"hljs-tag\">&lt;/<span class=\"hljs-name\">Col</span>&gt;</span>\n            <span class=\"hljs-tag\">&lt;<span class=\"hljs-name\">Col</span> <span class=\"hljs-attr\">span</span>=<span class=\"hljs-string\">\"4\"</span> <span class=\"hljs-attr\">style</span>=<span class=\"hljs-string\">\"height: 60px\"</span>&gt;</span>col-4<span class=\"hljs-tag\">&lt;/<span class=\"hljs-name\">Col</span>&gt;</span>\n            <span class=\"hljs-tag\">&lt;<span class=\"hljs-name\">Col</span> <span class=\"hljs-attr\">span</span>=<span class=\"hljs-string\">\"4\"</span> <span class=\"hljs-attr\">style</span>=<span class=\"hljs-string\">\"height: 80px\"</span>&gt;</span>col-4<span class=\"hljs-tag\">&lt;/<span class=\"hljs-name\">Col</span>&gt;</span>\n            <span class=\"hljs-tag\">&lt;<span class=\"hljs-name\">Col</span> <span class=\"hljs-attr\">span</span>=<span class=\"hljs-string\">\"4\"</span> <span class=\"hljs-attr\">style</span>=<span class=\"hljs-string\">\"height: 40px\"</span>&gt;</span>col-4<span class=\"hljs-tag\">&lt;/<span class=\"hljs-name\">Col</span>&gt;</span>\n        <span class=\"hljs-tag\">&lt;/<span class=\"hljs-name\">Row</span>&gt;</span>\n        <span class=\"hljs-tag\">&lt;<span class=\"hljs-name\">h5</span>&gt;</span>撑开成容器高度 stretch<span class=\"hljs-tag\">&lt;/<span class=\"hljs-name\">h5</span>&gt;</span>\n        <span class=\"hljs-tag\">&lt;<span class=\"hljs-name\">Row</span> <span class=\"hljs-attr\">align</span>=<span class=\"hljs-string\">\"stretch\"</span> <span class=\"hljs-attr\">justify</span>=<span class=\"hljs-string\">\"center\"</span> <span class=\"hljs-attr\">style</span>=<span class=\"hljs-string\">\"height: 100px;\"</span>&gt;</span> \n            <span class=\"hljs-tag\">&lt;<span class=\"hljs-name\">Col</span> <span class=\"hljs-attr\">span</span>=<span class=\"hljs-string\">\"4\"</span>&gt;</span>col-4<span class=\"hljs-tag\">&lt;/<span class=\"hljs-name\">Col</span>&gt;</span>\n            <span class=\"hljs-tag\">&lt;<span class=\"hljs-name\">Col</span> <span class=\"hljs-attr\">span</span>=<span class=\"hljs-string\">\"4\"</span>&gt;</span>col-4<span class=\"hljs-tag\">&lt;/<span class=\"hljs-name\">Col</span>&gt;</span>\n            <span class=\"hljs-tag\">&lt;<span class=\"hljs-name\">Col</span> <span class=\"hljs-attr\">span</span>=<span class=\"hljs-string\">\"4\"</span>&gt;</span>col-4<span class=\"hljs-tag\">&lt;/<span class=\"hljs-name\">Col</span>&gt;</span>\n            <span class=\"hljs-tag\">&lt;<span class=\"hljs-name\">Col</span> <span class=\"hljs-attr\">span</span>=<span class=\"hljs-string\">\"4\"</span>&gt;</span>col-4<span class=\"hljs-tag\">&lt;/<span class=\"hljs-name\">Col</span>&gt;</span>\n        <span class=\"hljs-tag\">&lt;/<span class=\"hljs-name\">Row</span>&gt;</span>\n        <span class=\"hljs-tag\">&lt;<span class=\"hljs-name\">h5</span>&gt;</span>基线对齐 baseline<span class=\"hljs-tag\">&lt;/<span class=\"hljs-name\">h5</span>&gt;</span>\n        <span class=\"hljs-tag\">&lt;<span class=\"hljs-name\">Row</span> <span class=\"hljs-attr\">align</span>=<span class=\"hljs-string\">\"baseline\"</span> <span class=\"hljs-attr\">justify</span>=<span class=\"hljs-string\">\"center\"</span>&gt;</span> \n            <span class=\"hljs-tag\">&lt;<span class=\"hljs-name\">Col</span> <span class=\"hljs-attr\">span</span>=<span class=\"hljs-string\">\"4\"</span> <span class=\"hljs-attr\">style</span>=<span class=\"hljs-string\">\"height: 100px; font-size: 20px\"</span>&gt;</span>col-4<span class=\"hljs-tag\">&lt;/<span class=\"hljs-name\">Col</span>&gt;</span>\n            <span class=\"hljs-tag\">&lt;<span class=\"hljs-name\">Col</span> <span class=\"hljs-attr\">span</span>=<span class=\"hljs-string\">\"4\"</span> <span class=\"hljs-attr\">style</span>=<span class=\"hljs-string\">\"height: 60px; font-size: 16px\"</span>&gt;</span>col-4<span class=\"hljs-tag\">&lt;/<span class=\"hljs-name\">Col</span>&gt;</span>\n            <span class=\"hljs-tag\">&lt;<span class=\"hljs-name\">Col</span> <span class=\"hljs-attr\">span</span>=<span class=\"hljs-string\">\"4\"</span> <span class=\"hljs-attr\">style</span>=<span class=\"hljs-string\">\"height: 80px; font-size: 28px\"</span>&gt;</span>col-4<span class=\"hljs-tag\">&lt;/<span class=\"hljs-name\">Col</span>&gt;</span>\n            <span class=\"hljs-tag\">&lt;<span class=\"hljs-name\">Col</span> <span class=\"hljs-attr\">span</span>=<span class=\"hljs-string\">\"4\"</span> <span class=\"hljs-attr\">style</span>=<span class=\"hljs-string\">\"height: 40px; font-size: 12px\"</span>&gt;</span>col-4<span class=\"hljs-tag\">&lt;/<span class=\"hljs-name\">Col</span>&gt;</span>\n        <span class=\"hljs-tag\">&lt;/<span class=\"hljs-name\">Row</span>&gt;</span>\n    <span class=\"hljs-tag\">&lt;/<span class=\"hljs-name\">div</span>&gt;</span>\n<span class=\"hljs-tag\">&lt;/<span class=\"hljs-name\">template</span>&gt;</span>\n<span class=\"hljs-tag\">&lt;<span class=\"hljs-name\">script</span>&gt;</span><span class=\"javascript\">\n<span class=\"hljs-keyword\">import</span> {Row, Col} <span class=\"hljs-keyword\">from</span> <span class=\"hljs-string\">'kpc/components/grid'</span>;\n\n<span class=\"hljs-keyword\">export</span> <span class=\"hljs-keyword\">default</span> {\n    <span class=\"hljs-attr\">components</span>: {\n        Row, Col\n    },\n}\n</span><span class=\"hljs-tag\">&lt;/<span class=\"hljs-name\">script</span>&gt;</span></code></pre>"
        },
        {
            "language": "jsx",
            "content": "<pre><code class=\"hljs jsx\"><span class=\"hljs-keyword\">import</span> React <span class=\"hljs-keyword\">from</span> <span class=\"hljs-string\">'react'</span>;\n<span class=\"hljs-keyword\">import</span> {Row, Col} <span class=\"hljs-keyword\">from</span> <span class=\"hljs-string\">'kpc/components/grid'</span>;\n\n<span class=\"hljs-keyword\">export</span> <span class=\"hljs-keyword\">default</span> <span class=\"hljs-class\"><span class=\"hljs-keyword\">class</span> <span class=\"hljs-keyword\">extends</span> <span class=\"hljs-title\">React</span>.<span class=\"hljs-title\">Component</span> </span>{\n    render() {\n        <span class=\"hljs-keyword\">return</span> (\n            <span class=\"xml\"><span class=\"hljs-tag\">&lt;<span class=\"hljs-name\">div</span>&gt;</span>\n                <span class=\"hljs-tag\">&lt;<span class=\"hljs-name\">h5</span>&gt;</span>顶端对齐 top<span class=\"hljs-tag\">&lt;/<span class=\"hljs-name\">h5</span>&gt;</span>\n                <span class=\"hljs-tag\">&lt;<span class=\"hljs-name\">Row</span> <span class=\"hljs-attr\">align</span>=<span class=\"hljs-string\">\"top\"</span> <span class=\"hljs-attr\">justify</span>=<span class=\"hljs-string\">\"center\"</span>&gt;</span> \n                    <span class=\"hljs-tag\">&lt;<span class=\"hljs-name\">Col</span> <span class=\"hljs-attr\">span</span>=<span class=\"hljs-string\">\"4\"</span> <span class=\"hljs-attr\">style</span>=<span class=\"hljs-string\">{{</span>\"<span class=\"hljs-attr\">height</span>\"<span class=\"hljs-attr\">:</span>\"<span class=\"hljs-attr\">100px</span>\"}}&gt;</span>col-4<span class=\"hljs-tag\">&lt;/<span class=\"hljs-name\">Col</span>&gt;</span>\n                    <span class=\"hljs-tag\">&lt;<span class=\"hljs-name\">Col</span> <span class=\"hljs-attr\">span</span>=<span class=\"hljs-string\">\"4\"</span> <span class=\"hljs-attr\">style</span>=<span class=\"hljs-string\">{{</span>\"<span class=\"hljs-attr\">height</span>\"<span class=\"hljs-attr\">:</span>\"<span class=\"hljs-attr\">60px</span>\"}}&gt;</span>col-4<span class=\"hljs-tag\">&lt;/<span class=\"hljs-name\">Col</span>&gt;</span>\n                    <span class=\"hljs-tag\">&lt;<span class=\"hljs-name\">Col</span> <span class=\"hljs-attr\">span</span>=<span class=\"hljs-string\">\"4\"</span> <span class=\"hljs-attr\">style</span>=<span class=\"hljs-string\">{{</span>\"<span class=\"hljs-attr\">height</span>\"<span class=\"hljs-attr\">:</span>\"<span class=\"hljs-attr\">80px</span>\"}}&gt;</span>col-4<span class=\"hljs-tag\">&lt;/<span class=\"hljs-name\">Col</span>&gt;</span>\n                    <span class=\"hljs-tag\">&lt;<span class=\"hljs-name\">Col</span> <span class=\"hljs-attr\">span</span>=<span class=\"hljs-string\">\"4\"</span> <span class=\"hljs-attr\">style</span>=<span class=\"hljs-string\">{{</span>\"<span class=\"hljs-attr\">height</span>\"<span class=\"hljs-attr\">:</span>\"<span class=\"hljs-attr\">40px</span>\"}}&gt;</span>col-4<span class=\"hljs-tag\">&lt;/<span class=\"hljs-name\">Col</span>&gt;</span>\n                <span class=\"hljs-tag\">&lt;/<span class=\"hljs-name\">Row</span>&gt;</span>\n                <span class=\"hljs-tag\">&lt;<span class=\"hljs-name\">h5</span>&gt;</span>底部对齐 bottom<span class=\"hljs-tag\">&lt;/<span class=\"hljs-name\">h5</span>&gt;</span>\n                <span class=\"hljs-tag\">&lt;<span class=\"hljs-name\">Row</span> <span class=\"hljs-attr\">align</span>=<span class=\"hljs-string\">\"bottom\"</span> <span class=\"hljs-attr\">justify</span>=<span class=\"hljs-string\">\"center\"</span>&gt;</span> \n                    <span class=\"hljs-tag\">&lt;<span class=\"hljs-name\">Col</span> <span class=\"hljs-attr\">span</span>=<span class=\"hljs-string\">\"4\"</span> <span class=\"hljs-attr\">style</span>=<span class=\"hljs-string\">{{</span>\"<span class=\"hljs-attr\">height</span>\"<span class=\"hljs-attr\">:</span>\"<span class=\"hljs-attr\">100px</span>\"}}&gt;</span>col-4<span class=\"hljs-tag\">&lt;/<span class=\"hljs-name\">Col</span>&gt;</span>\n                    <span class=\"hljs-tag\">&lt;<span class=\"hljs-name\">Col</span> <span class=\"hljs-attr\">span</span>=<span class=\"hljs-string\">\"4\"</span> <span class=\"hljs-attr\">style</span>=<span class=\"hljs-string\">{{</span>\"<span class=\"hljs-attr\">height</span>\"<span class=\"hljs-attr\">:</span>\"<span class=\"hljs-attr\">60px</span>\"}}&gt;</span>col-4<span class=\"hljs-tag\">&lt;/<span class=\"hljs-name\">Col</span>&gt;</span>\n                    <span class=\"hljs-tag\">&lt;<span class=\"hljs-name\">Col</span> <span class=\"hljs-attr\">span</span>=<span class=\"hljs-string\">\"4\"</span> <span class=\"hljs-attr\">style</span>=<span class=\"hljs-string\">{{</span>\"<span class=\"hljs-attr\">height</span>\"<span class=\"hljs-attr\">:</span>\"<span class=\"hljs-attr\">80px</span>\"}}&gt;</span>col-4<span class=\"hljs-tag\">&lt;/<span class=\"hljs-name\">Col</span>&gt;</span>\n                    <span class=\"hljs-tag\">&lt;<span class=\"hljs-name\">Col</span> <span class=\"hljs-attr\">span</span>=<span class=\"hljs-string\">\"4\"</span> <span class=\"hljs-attr\">style</span>=<span class=\"hljs-string\">{{</span>\"<span class=\"hljs-attr\">height</span>\"<span class=\"hljs-attr\">:</span>\"<span class=\"hljs-attr\">40px</span>\"}}&gt;</span>col-4<span class=\"hljs-tag\">&lt;/<span class=\"hljs-name\">Col</span>&gt;</span>\n                <span class=\"hljs-tag\">&lt;/<span class=\"hljs-name\">Row</span>&gt;</span>\n                <span class=\"hljs-tag\">&lt;<span class=\"hljs-name\">h5</span>&gt;</span>居中对齐 middle<span class=\"hljs-tag\">&lt;/<span class=\"hljs-name\">h5</span>&gt;</span>\n                <span class=\"hljs-tag\">&lt;<span class=\"hljs-name\">Row</span> <span class=\"hljs-attr\">align</span>=<span class=\"hljs-string\">\"middle\"</span> <span class=\"hljs-attr\">justify</span>=<span class=\"hljs-string\">\"center\"</span>&gt;</span> \n                    <span class=\"hljs-tag\">&lt;<span class=\"hljs-name\">Col</span> <span class=\"hljs-attr\">span</span>=<span class=\"hljs-string\">\"4\"</span> <span class=\"hljs-attr\">style</span>=<span class=\"hljs-string\">{{</span>\"<span class=\"hljs-attr\">height</span>\"<span class=\"hljs-attr\">:</span>\"<span class=\"hljs-attr\">100px</span>\"}}&gt;</span>col-4<span class=\"hljs-tag\">&lt;/<span class=\"hljs-name\">Col</span>&gt;</span>\n                    <span class=\"hljs-tag\">&lt;<span class=\"hljs-name\">Col</span> <span class=\"hljs-attr\">span</span>=<span class=\"hljs-string\">\"4\"</span> <span class=\"hljs-attr\">style</span>=<span class=\"hljs-string\">{{</span>\"<span class=\"hljs-attr\">height</span>\"<span class=\"hljs-attr\">:</span>\"<span class=\"hljs-attr\">60px</span>\"}}&gt;</span>col-4<span class=\"hljs-tag\">&lt;/<span class=\"hljs-name\">Col</span>&gt;</span>\n                    <span class=\"hljs-tag\">&lt;<span class=\"hljs-name\">Col</span> <span class=\"hljs-attr\">span</span>=<span class=\"hljs-string\">\"4\"</span> <span class=\"hljs-attr\">style</span>=<span class=\"hljs-string\">{{</span>\"<span class=\"hljs-attr\">height</span>\"<span class=\"hljs-attr\">:</span>\"<span class=\"hljs-attr\">80px</span>\"}}&gt;</span>col-4<span class=\"hljs-tag\">&lt;/<span class=\"hljs-name\">Col</span>&gt;</span>\n                    <span class=\"hljs-tag\">&lt;<span class=\"hljs-name\">Col</span> <span class=\"hljs-attr\">span</span>=<span class=\"hljs-string\">\"4\"</span> <span class=\"hljs-attr\">style</span>=<span class=\"hljs-string\">{{</span>\"<span class=\"hljs-attr\">height</span>\"<span class=\"hljs-attr\">:</span>\"<span class=\"hljs-attr\">40px</span>\"}}&gt;</span>col-4<span class=\"hljs-tag\">&lt;/<span class=\"hljs-name\">Col</span>&gt;</span>\n                <span class=\"hljs-tag\">&lt;/<span class=\"hljs-name\">Row</span>&gt;</span>\n                <span class=\"hljs-tag\">&lt;<span class=\"hljs-name\">h5</span>&gt;</span>撑开成容器高度 stretch<span class=\"hljs-tag\">&lt;/<span class=\"hljs-name\">h5</span>&gt;</span>\n                <span class=\"hljs-tag\">&lt;<span class=\"hljs-name\">Row</span> <span class=\"hljs-attr\">align</span>=<span class=\"hljs-string\">\"stretch\"</span> <span class=\"hljs-attr\">justify</span>=<span class=\"hljs-string\">\"center\"</span> <span class=\"hljs-attr\">style</span>=<span class=\"hljs-string\">{{</span>\"<span class=\"hljs-attr\">height</span>\"<span class=\"hljs-attr\">:</span>\"<span class=\"hljs-attr\">100px</span>\"}}&gt;</span> \n                    <span class=\"hljs-tag\">&lt;<span class=\"hljs-name\">Col</span> <span class=\"hljs-attr\">span</span>=<span class=\"hljs-string\">\"4\"</span>&gt;</span>col-4<span class=\"hljs-tag\">&lt;/<span class=\"hljs-name\">Col</span>&gt;</span>\n                    <span class=\"hljs-tag\">&lt;<span class=\"hljs-name\">Col</span> <span class=\"hljs-attr\">span</span>=<span class=\"hljs-string\">\"4\"</span>&gt;</span>col-4<span class=\"hljs-tag\">&lt;/<span class=\"hljs-name\">Col</span>&gt;</span>\n                    <span class=\"hljs-tag\">&lt;<span class=\"hljs-name\">Col</span> <span class=\"hljs-attr\">span</span>=<span class=\"hljs-string\">\"4\"</span>&gt;</span>col-4<span class=\"hljs-tag\">&lt;/<span class=\"hljs-name\">Col</span>&gt;</span>\n                    <span class=\"hljs-tag\">&lt;<span class=\"hljs-name\">Col</span> <span class=\"hljs-attr\">span</span>=<span class=\"hljs-string\">\"4\"</span>&gt;</span>col-4<span class=\"hljs-tag\">&lt;/<span class=\"hljs-name\">Col</span>&gt;</span>\n                <span class=\"hljs-tag\">&lt;/<span class=\"hljs-name\">Row</span>&gt;</span>\n                <span class=\"hljs-tag\">&lt;<span class=\"hljs-name\">h5</span>&gt;</span>基线对齐 baseline<span class=\"hljs-tag\">&lt;/<span class=\"hljs-name\">h5</span>&gt;</span>\n                <span class=\"hljs-tag\">&lt;<span class=\"hljs-name\">Row</span> <span class=\"hljs-attr\">align</span>=<span class=\"hljs-string\">\"baseline\"</span> <span class=\"hljs-attr\">justify</span>=<span class=\"hljs-string\">\"center\"</span>&gt;</span> \n                    <span class=\"hljs-tag\">&lt;<span class=\"hljs-name\">Col</span> <span class=\"hljs-attr\">span</span>=<span class=\"hljs-string\">\"4\"</span> <span class=\"hljs-attr\">style</span>=<span class=\"hljs-string\">{{</span>\"<span class=\"hljs-attr\">height</span>\"<span class=\"hljs-attr\">:</span>\"<span class=\"hljs-attr\">100px</span>\",\"<span class=\"hljs-attr\">fontSize</span>\"<span class=\"hljs-attr\">:</span>\"<span class=\"hljs-attr\">20px</span>\"}}&gt;</span>col-4<span class=\"hljs-tag\">&lt;/<span class=\"hljs-name\">Col</span>&gt;</span>\n                    <span class=\"hljs-tag\">&lt;<span class=\"hljs-name\">Col</span> <span class=\"hljs-attr\">span</span>=<span class=\"hljs-string\">\"4\"</span> <span class=\"hljs-attr\">style</span>=<span class=\"hljs-string\">{{</span>\"<span class=\"hljs-attr\">height</span>\"<span class=\"hljs-attr\">:</span>\"<span class=\"hljs-attr\">60px</span>\",\"<span class=\"hljs-attr\">fontSize</span>\"<span class=\"hljs-attr\">:</span>\"<span class=\"hljs-attr\">16px</span>\"}}&gt;</span>col-4<span class=\"hljs-tag\">&lt;/<span class=\"hljs-name\">Col</span>&gt;</span>\n                    <span class=\"hljs-tag\">&lt;<span class=\"hljs-name\">Col</span> <span class=\"hljs-attr\">span</span>=<span class=\"hljs-string\">\"4\"</span> <span class=\"hljs-attr\">style</span>=<span class=\"hljs-string\">{{</span>\"<span class=\"hljs-attr\">height</span>\"<span class=\"hljs-attr\">:</span>\"<span class=\"hljs-attr\">80px</span>\",\"<span class=\"hljs-attr\">fontSize</span>\"<span class=\"hljs-attr\">:</span>\"<span class=\"hljs-attr\">28px</span>\"}}&gt;</span>col-4<span class=\"hljs-tag\">&lt;/<span class=\"hljs-name\">Col</span>&gt;</span>\n                    <span class=\"hljs-tag\">&lt;<span class=\"hljs-name\">Col</span> <span class=\"hljs-attr\">span</span>=<span class=\"hljs-string\">\"4\"</span> <span class=\"hljs-attr\">style</span>=<span class=\"hljs-string\">{{</span>\"<span class=\"hljs-attr\">height</span>\"<span class=\"hljs-attr\">:</span>\"<span class=\"hljs-attr\">40px</span>\",\"<span class=\"hljs-attr\">fontSize</span>\"<span class=\"hljs-attr\">:</span>\"<span class=\"hljs-attr\">12px</span>\"}}&gt;</span>col-4<span class=\"hljs-tag\">&lt;/<span class=\"hljs-name\">Col</span>&gt;</span>\n                <span class=\"hljs-tag\">&lt;/<span class=\"hljs-name\">Row</span>&gt;</span>\n            <span class=\"hljs-tag\">&lt;/<span class=\"hljs-name\">div</span>&gt;</span></span>\n        )\n    }\n}</code></pre>"
        }
    ]
}